Metadata-Version: 2.4
Name: fractek
Version: 0.1.1.post1
Summary: A world-class modular fractal mathematics, visualization, and analysis library
Home-page: https://github.com/thynash/fractek
Author: Nityansh Pant
Author-email: pantnityansh@gmail.com
License: MIT
Keywords: fractal mathematics visualization analysis dimensional fractal-noise
Classifier: Programming Language :: Python :: 3
Classifier: License :: OSI Approved :: MIT License
Classifier: Operating System :: OS Independent
Classifier: Topic :: Scientific/Engineering :: Mathematics
Classifier: Intended Audience :: Science/Research
Classifier: Intended Audience :: Developers
Classifier: Natural Language :: English
Requires-Python: >=3.8
License-File: LICENSE
Requires-Dist: numpy>=1.19
Requires-Dist: matplotlib>=3.4
Requires-Dist: scipy>=1.7
Requires-Dist: noise>=1.2.2
Dynamic: author
Dynamic: author-email
Dynamic: classifier
Dynamic: description
Dynamic: description-content-type
Dynamic: home-page
Dynamic: keywords
Dynamic: license
Dynamic: license-file
Dynamic: requires-dist
Dynamic: requires-python
Dynamic: summary
